[
  {
    "id": "amber-oud",
    "name": "Amber Oud",
    "price": 99,
    "description": "Amber Oud captures the essence of eternal summer. Zesty citrus bursts into a cascade of ripe fruits — an intoxicating dance of sweetness and light. As the day fades, velvety vanilla, white musk, and amber weave a silken trail of warmth and allure. A fragrance of pure joy and sensual sophistication —vibrant, long-lasting, and irresistibly magnetic.",
    "category": "blends",
    "gender": "Unisex",
    "image": "/images/aggaroud/IMG_0002.JPG",
    "images": [
      "/images/aggaroud/IMG_0002.JPG",
      "/images/aggaroud/IMG_0007.JPG",
      "/images/aggaroud/IMG_0008.JPG"
    ],
    "top": "Bergamot, Mandarin, Hyacinth, Pineapple",
    "heart": "Loganberry, Orris, Jasmine, Pink Pepper",
    "base": "Amber, Musk, Sandalwood, Vanilla, Oud",
    "variants": [
      {
        "id": "6ml",
        "size": "6ml",
        "price": 99
      },
      {
        "id": "12ml",
        "size": "12ml",
        "price": 179
      }
    ],
    "inStock": true,
    "featured": true
  },
  {
    "id": "pure-oud-royale",
    "name": "Pure Oud Royale",
    "price": 499,
    "description": "100% pure agarwood oil from the finest sources. Uncut, authentic, and rare.",
    "category": "pure-oud",
    "gender": "Men",
    "image": "/images/aggaroud/IMG_0007.JPG",
    "images": [
      "/images/aggaroud/IMG_0007.JPG",
      "/images/aggaroud/IMG_0002.JPG"
    ],
    "inStock": true,
    "featured": true
  },
  {
    "id": "mystic-blend",
    "name": "Mystic Blend",
    "price": 349,
    "description": "A mysterious fusion of oud, sandalwood, and exotic spices. Captivating and timeless.",
    "category": "blends",
    "gender": "Men",
    "image": "/images/aggaroud/IMG_0008.JPG",
    "images": [
      "/images/aggaroud/IMG_0008.JPG",
      "/images/aggaroud/IMG_0002.JPG"
    ],
    "inStock": true,
    "featured": true
  },
  {
    "id": "saffron-oud",
    "name": "Saffron Oud",
    "price": 279,
    "description": "Golden saffron threads intertwined with rich oud. Opulent and refined.",
    "category": "blends",
    "gender": "Unisex",
    "image": "/images/aggaroud/IMG_0002.JPG",
    "images": [
      "/images/aggaroud/IMG_0002.JPG"
    ],
    "inStock": true,
    "featured": false
  },
  {
    "id": "cambodian-oud",
    "name": "Cambodian Oud",
    "price": 599,
    "description": "Rare Cambodian agarwood with deep, complex notes. For true connoisseurs.",
    "category": "pure-oud",
    "gender": "Men",
    "image": "/images/aggaroud/IMG_0007.JPG",
    "images": [
      "/images/aggaroud/IMG_0007.JPG"
    ],
    "inStock": true,
    "featured": false
  },
  {
    "id": "rose-oud",
    "name": "Rose Oud",
    "price": 329,
    "description": "Delicate rose petals meet earthy oud. A perfect harmony of floral and woody.",
    "category": "blends",
    "gender": "Women",
    "image": "/images/aggaroud/IMG_0008.JPG",
    "images": [
      "/images/aggaroud/IMG_0008.JPG"
    ],
    "inStock": true,
    "featured": false
  }
]